cursofiap/__init__.py
cursofiap/core.py
hello_world_fiap_package-1.0.0.dist-info/METADATA
hello_world_fiap_package-1.0.0.dist-info/WHEEL
hello_world_fiap_package-1.0.0.dist-info/top_level.txt
hello_world_fiap_package-1.0.0.dist-info/RECORD
