Metadata-Version: 2.4
Name: hello-world-fiap-package
Version: 1.0.0
Summary: Descricao da sua lib cursofiap
Home-page: https://github.com/patrickmeirelles
Author: Patrick Meirelles
Author-email: seu.email@example.com
License: MIT
Dynamic: author
Dynamic: author-email
Dynamic: description
Dynamic: description-content-type
Dynamic: home-page
Dynamic: license
Dynamic: summary
